jupyterlab_vega3/__init__.py
jupyterlab_vega3/_version.py
jupyterlab_vega3-3.3.0.data/data/share/jupyter/labextensions/@jupyterlab/vega3-extension/package.json
jupyterlab_vega3-3.3.0.data/data/share/jupyter/labextensions/@jupyterlab/vega3-extension/static/45.9a59d4b302094f275e9f.js
jupyterlab_vega3-3.3.0.data/data/share/jupyter/labextensions/@jupyterlab/vega3-extension/static/568.d77addb1f5a8d99f6e42.js
jupyterlab_vega3-3.3.0.data/data/share/jupyter/labextensions/@jupyterlab/vega3-extension/static/643.b29fe3063574dc8d1af5.js
jupyterlab_vega3-3.3.0.data/data/share/jupyter/labextensions/@jupyterlab/vega3-extension/static/72.7a3f283ffd842e9b9289.js
jupyterlab_vega3-3.3.0.data/data/share/jupyter/labextensions/@jupyterlab/vega3-extension/static/72.7a3f283ffd842e9b9289.js.LICENSE.txt
jupyterlab_vega3-3.3.0.data/data/share/jupyter/labextensions/@jupyterlab/vega3-extension/static/remoteEntry.a502c21424f3610e2657.js
jupyterlab_vega3-3.3.0.data/data/share/jupyter/labextensions/@jupyterlab/vega3-extension/static/style.js
jupyterlab_vega3-3.3.0.data/data/share/jupyter/labextensions/@jupyterlab/vega3-extension/static/third-party-licenses.json
jupyterlab_vega3-3.3.0.data/data/share/jupyter/labextensions/@jupyterlab/vega3-extension/install.json
jupyterlab_vega3-3.3.0.dist-info/METADATA
jupyterlab_vega3-3.3.0.dist-info/WHEEL
jupyterlab_vega3-3.3.0.dist-info/licenses/LICENSE
jupyterlab_vega3-3.3.0.dist-info/RECORD
